{
  "id": "HHS-ONC-2025-0005-0282",
  "commenter_name": "Invest for Progress",
  "organization": "Invest for Progress",
  "posted_date": "2026-03-02T05:00:00Z",
  "has_text": true,
  "comment_length": 63,
  "org_type": "other",
  "summary": "Invest for Progress submitted comments on the HTI-5 proposed rule but did not provide substantive content in the comment text. The comment is a placeholder indicating attached comments were submitted separately.",
  "position": "neutral_mixed",
  "key_themes": [],
  "specific_provisions": [],
  "key_arguments": [],
  "recommendations": [],
  "sentiment_score": 0,
  "notable_quote": "Invest for Progress is pleased to submit the attached comments."
}
