{
  "id": "HHS-ONC-2025-0005-0242",
  "title": "Comment from athenahealth, HHS-ONC-2025-0005, HHS-ONC-2025-0005-0001, 2025-23896",
  "commenter_name": "athenahealth",
  "commenter_first": "",
  "commenter_last": "",
  "organization": "athenahealth",
  "gov_agency": "",
  "gov_agency_type": "",
  "city": "",
  "state": "",
  "country": "",
  "posted_date": "2026-03-02T05:00:00Z",
  "received_date": "2026-02-27T05:00:00Z",
  "page_count": 1,
  "comment_text": "athenahealth appreciates the opportunity to respond to the proposed changes outlined in the Health Data, Technology, and Interoperability: ASTP/ONC Deregulatory Actions To Unleash Prosperity proposed rule. Please see our attached comments.\nThank you,\nJennifer Michaels",
  "has_attachments": true,
  "attachments": [
    {
      "title": "athenahealth comments on ONC HTI-5 Proposed Rule",
      "filename": "",
      "url": "https://downloads.regulations.gov/HHS-ONC-2025-0005-0242/attachment_1.pdf",
      "format": "pdf"
    },
    {
      "title": "image",
      "filename": "",
      "url": "https://downloads.regulations.gov/HHS-ONC-2025-0005-0242/attachment_2.pdf",
      "format": "pdf"
    },
    {
      "title": "image",
      "filename": "",
      "url": "https://downloads.regulations.gov/HHS-ONC-2025-0005-0242/attachment_2.png",
      "format": "png"
    }
  ],
  "doc_abstract": ""
}
