{
  "id": "HHS-ONC-2025-0005-0304",
  "title": "Comment on HHS-ONC-2025-0005, HHS-ONC-2025-0005-0001, 2025-23896",
  "commenter_name": "Anonymous Anonymous",
  "commenter_first": "Anonymous",
  "commenter_last": "Anonymous",
  "organization": "",
  "gov_agency": "",
  "gov_agency_type": "",
  "city": "",
  "state": "",
  "country": "",
  "posted_date": "2026-03-02T05:00:00Z",
  "received_date": "2026-02-27T05:00:00Z",
  "page_count": 1,
  "comment_text": "First, I do appreciate the proposal&rsquo;s purpose of updating current regulations around health data, technology, and interoperability. The rapid AI adoption in healthcare warrants regulations that encourages healthy competitive markets while maintaining the integrity and safety of a patient&rsquo;s individual health care. \nHowever, I implore you to revisit the proposal&rsquo;s plan for Certification Criteria for Health Information Technology. Of the current 60 criteria, 34 are being removed and 7 revised. What poses the greatest threat to the integrity and safety of health care data are: \nthe removal of: \n&sect; 170.315(d)(1): Authentication, access control, authorization \n&sect; 170.315(d)(2): Auditable events and tamper-resistance \n&sect; 170.315(d)(3): Audit report(s) \n&sect; 170.315(d)(4): Amendments\n&sect; 170.315(d)(5): Automatic access time-out \n&sect; 170.315(d)(6): Emergency access \n&sect; 170.315(d)(7): End-user device encryption \n&sect; 170.315(d)(8): Integrity \n&sect; 170.315(d)(9): Trusted connection \n&sect; 170.315(d)(12): Encrypt authentication credentials \n&sect; 170.315(d)(13): Multi-factor authentication (MFA)\nand the revision of: \n&sect; 170.315(b)(11): Decision Support Interventions (DSI)\nThe ASTP/ONC justifies the removals and revisions by stating they are &ldquo;redundant&rdquo; of the HIPAA Security Rule. This argument ultimately fails to account for the functional difference between product-level certification and organizational-level compliance. By removing the 11 security criteria, the ASTP/ONC effectively shifts the technical vetting burden from a federal testing process to the health care providers/organizations This is not a net reduction in industry burden. It now becomes a massive unfunded mandate for individual health care organizations to perform manual, product-specific technical audits that were previously covered by the &ldquo;Certified Health IT&rdquo; certification. \nThe revision of &sect; 170.315(b)(11) will inevitably trigger a significant regression in clinical safety. Removing the &ldquo;Model Card&rdquo; deletes the 31 attributes that are required for developers to share. This would mean clinicians will no longer see how the AI was built or tested. In the eyes of health risk management, removal of the label no longer guarantees that the AI-model has been vetted. Health organizations will now inherit 100% of the risk. \nThis proposal ultimately shifts the burden of risk, integrity, and patient safety wholly to providers and health organizations. It correctly identifies the cost of regulation to developers but it fails to consider for the multiplied costs to the healthcare delivery system. At its core, this proposal is a systemic transfer of liability.",
  "has_attachments": false,
  "attachments": [],
  "doc_abstract": ""
}
